{
    "department": "Mechanical & Mechatronics",
    "general_instructions": {
        "id_card": "College ID is mandatory for all participants.",
        "team_size_general": "Maximum 3 members per team.",
        "punctuality": "Teams must report 15 minutes before the event starts.",
        "decorum": "Judge's decisions are final. Malpractice leads to immediate disqualification."
    },
    "technical_events": [
        {
            "id": "mech-paper",
            "event_name": "Paper Presentation (3D Printing, Robotics, AI, Drones)",
            "rules": [
                "Detailed rules will be updated soon."
            ]
        },
        {
            "id": "mech-cad",
            "event_name": "CAD Modeling",
            "rules": [
                "Detailed rules will be updated soon."
            ]
        },
        {
            "id": "mech-calibre",
            "event_name": "Calibre",
            "rules": [
                "Detailed rules will be updated soon."
            ]
        },
        {
            "id": "mech-quiz",
            "event_name": "Technical Quiz",
            "rules": [
                "Detailed rules will be updated soon."
            ]
        }
    ],
    "non_technical_events": [
        {
            "id": "mech-paper-events",
            "event_name": "Paper Events",
            "rules": [
                "Detailed rules will be updated soon."
            ]
        },
        {
            "id": "mech-painting",
            "event_name": "Brushless Painting",
            "rules": [
                "Detailed rules will be updated soon."
            ]
        }
    ]
}